bashbot_package/bashbot_index.py
bashbot_package-0.0.2.dist-info/LICENSE.txt
bashbot_package-0.0.2.dist-info/METADATA
bashbot_package-0.0.2.dist-info/WHEEL
bashbot_package-0.0.2.dist-info/entry_points.txt
bashbot_package-0.0.2.dist-info/top_level.txt
bashbot_package-0.0.2.dist-info/RECORD
