Metadata-Version: 2.1
Name: bashbot-package
Version: 0.0.2
Summary: a CLI tool for accessing ChatGPT + other useful features
Home-page: https://github.com/BaamAhmed/bashbot.git
Author: Bassam Ahmed
Author-email: b3ahmed@uwaterloo.ca
License-File: LICENSE.txt
Requires-Dist: flask
Requires-Dist: decouple
Requires-Dist: rich
Requires-Dist: openai
